omie_client/__init__.py
omie_client/accounts_payable.py
omie_client/bank_accounts.py
omie_client/client.py
omie_client/endpoint.py
omie_client/exceptions.py
omie_client/financial_movements.py
omie_client/model.py
omie_client/pagination.py
omie_client-0.3.0.dist-info/METADATA
omie_client-0.3.0.dist-info/WHEEL
omie_client-0.3.0.dist-info/RECORD
