Metadata-Version: 2.1
Name: omie-client
Version: 0.3.0
Summary: Omie Client Python SDK
Author: BHub Tech Team
Author-email: tech-team@bhub.ai
Requires-Python: >=3.9,<4.0
Classifier: Programming Language :: Python :: 3
Classifier: Programming Language :: Python :: 3.9
Classifier: Programming Language :: Python :: 3.10
Classifier: Programming Language :: Python :: 3.11
Classifier: Programming Language :: Python :: 3.12
Classifier: Topic :: Software Development :: Libraries
Classifier: Topic :: Software Development :: Libraries :: Python Modules
Requires-Dist: httpx[http2] (>=0.27.0,<0.28.0)
Requires-Dist: pydantic (>=2.7.4,<3.0.0)
